vaapi/__init__.py
vaapi/base_client.py
vaapi/client.py
vaapi/annotations/__init__.py
vaapi/annotations/client.py
vaapi/behavior_frame_option/__init__.py
vaapi/behavior_frame_option/client.py
vaapi/behavior_options/__init__.py
vaapi/behavior_options/client.py
vaapi/behavior_options_state/__init__.py
vaapi/behavior_options_state/client.py
vaapi/cognition_frame/__init__.py
vaapi/cognition_frame/client.py
vaapi/cognition_representation/__init__.py
vaapi/cognition_representation/client.py
vaapi/core/api_error.py
vaapi/core/client_wrapper.py
vaapi/core/datetime_utils.py
vaapi/core/file.py
vaapi/core/http_client.py
vaapi/core/jsonable_encoder.py
vaapi/core/pagination.py
vaapi/core/pydantic_utilities.py
vaapi/core/query_encoder.py
vaapi/core/remove_none_from_dict.py
vaapi/core/request_options.py
vaapi/events/__init__.py
vaapi/events/client.py
vaapi/experiment/__init__.py
vaapi/experiment/client.py
vaapi/frame_filter/__init__.py
vaapi/frame_filter/client.py
vaapi/game/__init__.py
vaapi/game/client.py
vaapi/image/__init__.py
vaapi/image/client.py
vaapi/log_status/__init__.py
vaapi/log_status/client.py
vaapi/logs/__init__.py
vaapi/logs/client.py
vaapi/motion_frame/__init__.py
vaapi/motion_frame/client.py
vaapi/motion_representation/__init__.py
vaapi/motion_representation/client.py
vaapi/robots/__init__.py
vaapi/robots/client.py
vaapi/teams/__init__.py
vaapi/teams/client.py
vaapi/timeline/__init__.py
vaapi/timeline/client.py
vaapi/types/annotation.py
vaapi/types/behavior_option.py
vaapi/types/behavior_option_state.py
vaapi/types/behaviorframe_options.py
vaapi/types/cognition_frame.py
vaapi/types/cognition_representation.py
vaapi/types/event.py
vaapi/types/experiment.py
vaapi/types/frame_filter.py
vaapi/types/game.py
vaapi/types/image.py
vaapi/types/log.py
vaapi/types/log_status.py
vaapi/types/motion_frame.py
vaapi/types/motion_representation.py
vaapi/types/robots.py
vaapi/types/teams.py
vaapi/types/timeline.py
vaapi/types/video.py
vaapi/types/xabsl_symbol_complete.py
vaapi-0.7.18.dist-info/METADATA
vaapi-0.7.18.dist-info/WHEEL
vaapi-0.7.18.dist-info/top_level.txt
vaapi-0.7.18.dist-info/RECORD
