Metadata-Version: 2.4
Name: vaapi
Version: 0.7.18
Summary: Python utils for adding logs to our Visual Analytics Tool
Author-email: NaoTH Berlin United <nao-team@informatik.hu-berlin.de>
License: Apache-2.0
Classifier: Programming Language :: Python :: 3
Classifier: License :: OSI Approved :: Apache Software License
Classifier: Operating System :: OS Independent
Requires-Python: >=3.10.9
Requires-Dist: protobuf==3.20.3
Requires-Dist: httpx==0.28.1
Requires-Dist: pydantic==2.12.5
Requires-Dist: requests==2.32.5
